odoo/addons/product_data_sheet/README.rst
odoo/addons/product_data_sheet/__init__.py
odoo/addons/product_data_sheet/__manifest__.py
odoo/addons/product_data_sheet/i18n/ca_ES.po
odoo/addons/product_data_sheet/i18n/es.po
odoo/addons/product_data_sheet/models/__init__.py
odoo/addons/product_data_sheet/models/mail_compose_message.py
odoo/addons/product_data_sheet/models/product_template.py
odoo/addons/product_data_sheet/static/description/icon.png
odoo/addons/product_data_sheet/views/mail_compose_message.xml
odoo/addons/product_data_sheet/views/product_template.xml
odoo11_addon_product_data_sheet-11.0.1.0.0.99.dev2.dist-info/METADATA
odoo11_addon_product_data_sheet-11.0.1.0.0.99.dev2.dist-info/WHEEL
odoo11_addon_product_data_sheet-11.0.1.0.0.99.dev2.dist-info/top_level.txt
odoo11_addon_product_data_sheet-11.0.1.0.0.99.dev2.dist-info/RECORD
